horse_race_simulator/race_data/horse_stats.py
horse_race_simulator/race_data/race_details.py
horse_race_simulator/race_data/track_data.py
horse_race_simulator/simulation/betting.py
horse_race_simulator/simulation/race_results.py
horse_race_simulator/simulation/race_simulator.py
Horsle-0.0.3.dist-info/LICENSE.txt
Horsle-0.0.3.dist-info/METADATA
Horsle-0.0.3.dist-info/WHEEL
Horsle-0.0.3.dist-info/top_level.txt
Horsle-0.0.3.dist-info/RECORD
